{
  "_class": "shapeGroup",
  "clippingMaskMode": 0,
  "do_objectID": "21F2457C-9C5F-4484-8EFD-33C71860E8DD",
  "exportOptions": {
    "_class": "exportOptions",
    "exportFormats": [
    ],
    "includedLayerIds": [
    ],
    "layerOptions": 0,
    "shouldTrim": false
  },
  "frame": {
    "_class": "rect",
    "constrainProportions": false,
    "height": 52.73437499999999,
    "width": 52.734375,
    "x": 0,
    "y": 0
  },
  "hasClickThrough": false,
  "hasClippingMask": false,
  "isFlippedHorizontal": false,
  "isFlippedVertical": false,
  "isLocked": false,
  "isVisible": true,
  "layerListExpandedType": 0,
  "layers": [
    {
      "class": "rectangle",
      "id": "9E55C0A0-1701-403E-9364-B102F8E199F0"
    }
  ],
  "name": "Rectangle 59",
  "nameIsFixed": false,
  "originalObjectID": "E8492B26-4F19-47BB-A752-FA947F4BEEFA",
  "resizingConstraint": 63,
  "resizingType": 0,
  "rotation": 0,
  "shouldBreakMaskChain": false,
  "style": {
    "_class": "style",
    "blur": {
      "_class": "blur",
      "center": "{0.5, 0.5}",
      "isEnabled": false,
      "motionAngle": 0,
      "radius": 11.71875,
      "type": 0
    },
    "borders": [
      {
        "_class": "border",
        "color": {
          "_class": "color",
          "alpha": 1,
          "blue": 0.791905824829932,
          "green": 0.791905824829932,
          "red": 0.791905824829932
        },
        "fillType": 0,
        "isEnabled": true,
        "position": 1,
        "thickness": 0.5859375
      }
    ],
    "endDecorationType": 0,
    "fills": [
      {
        "_class": "fill",
        "color": {
          "_class": "color",
          "alpha": 1,
          "blue": 1,
          "green": 1,
          "red": 1
        },
        "fillType": 0,
        "gradient": {
          "_class": "gradient",
          "elipseLength": 0,
          "from": "{0.11451822916666667, 0.1611328125}",
          "gradientType": 0,
          "shouldSmoothenOpacity": false,
          "stops": [
            {
              "_class": "gradientStop",
              "color": {
                "_class": "color",
                "alpha": 1,
                "blue": 1,
                "green": 1,
                "red": 1
              },
              "position": 0
            },
            {
              "_class": "gradientStop",
              "color": {
                "_class": "color",
                "alpha": 1,
                "blue": 0.7960784313725489,
                "green": 0.9333333333333333,
                "red": 0.3647058823529412
              },
              "position": 1
            }
          ],
          "to": "{0.85963541666666665, 0.82968750000000002}"
        },
        "isEnabled": true,
        "noiseIndex": 0,
        "noiseIntensity": 0,
        "patternFillType": 1,
        "patternTileScale": 1
      }
    ],
    "miterLimit": 10,
    "startDecorationType": 0
  },
  "windingRule": 1
}